landsat/__init__.py
landsat/decorators.py
landsat/downloader.py
landsat/image.py
landsat/landsat.py
landsat/mixins.py
landsat/ndvi.py
landsat/search.py
landsat/settings.py
landsat/uploader.py
landsat/utils.py
landsat/maps/colormap_cubehelix.txt
landsat/maps/colormap_ndvi.txt
landsat/maps/colormap_ndvi_cfastie.txt
landsat_util-0.12.1.data/scripts/landsat
landsat_util-0.12.1.dist-info/DESCRIPTION.rst
landsat_util-0.12.1.dist-info/METADATA
landsat_util-0.12.1.dist-info/RECORD
landsat_util-0.12.1.dist-info/WHEEL
landsat_util-0.12.1.dist-info/metadata.json
landsat_util-0.12.1.dist-info/top_level.txt
