Metadata-Version: 2.0
Name: landsat-util
Version: 0.12.1
Summary: A utility to search, download and process Landsat 8 satellite imagery
Home-page: https://github.com/developmentseed/landsat-util
Author: Development Seed
Author-email: info@developmentseed.org
License: CCO
Platform: Posix; MacOS X; Windows
Requires-Dist: boto (>=2.38.0)
Requires-Dist: geocoder (>=1.5.1)
Requires-Dist: homura (>=0.1.2)
Requires-Dist: numpy (>=1.9.3)
Requires-Dist: polyline (==1.1)
Requires-Dist: python-dateutil (>=2.4.2)
Requires-Dist: rasterio (>=0.26.0)
Requires-Dist: requests (==2.7.0)
Requires-Dist: scikit-image (>=0.11.3)
Requires-Dist: scipy (>=0.16.0)
Requires-Dist: six (==1.8.0)
Requires-Dist: termcolor (>=1.1.0)
Requires-Dist: usgs2 (==0.2.0)
